{"metadata": {"dbt_schema_version": "https://schemas.getdbt.com/dbt/run-results/v4.json", "dbt_version": "1.5.0", "generated_at": "2023-07-06T09:26:07.714505Z", "invocation_id": "faaee92f-7356-4e20-8752-5497dc8f97cb", "env": {}}, "results": [{"status": "success", "timing": [{"name": "compile", "started_at": "2023-07-06T09:25:46.882208Z", "completed_at": "2023-07-06T09:25:46.939167Z"}, {"name": "execute", "started_at": "2023-07-06T09:25:46.994105Z", "completed_at": "2023-07-06T09:25:50.183000Z"}], "thread_id": "Thread-3 (worker)", "execution_time": 3.3417928218841553, "adapter_response": {"_message": "SELECT 14610", "code": "SELECT", "rows_affected": 14610}, "message": "SELECT 14610", "failures": null, "unique_id": "model.metrics.dbt_metrics_default_calendar"}, {"status": "success", "timing": [{"name": "compile", "started_at": "2023-07-06T09:25:46.873205Z", "completed_at": "2023-07-06T09:25:46.927104Z"}, {"name": "execute", "started_at": "2023-07-06T09:25:46.985195Z", "completed_at": "2023-07-06T09:25:50.188972Z"}], "thread_id": "Thread-2 (worker)", "execution_time": 3.3468120098114014, "adapter_response": {"_message": "CREATE VIEW", "code": "CREATE VIEW", "rows_affected": -1}, "message": "CREATE VIEW", "failures": null, "unique_id": "model.jaffle_shop_metrics.stg_payments"}, {"status": "success", "timing": [{"name": "compile", "started_at": "2023-07-06T09:25:46.867190Z", "completed_at": "2023-07-06T09:25:46.924144Z"}, {"name": "execute", "started_at": "2023-07-06T09:25:46.928175Z", "completed_at": "2023-07-06T09:25:50.193949Z"}], "thread_id": "Thread-1 (worker)", "execution_time": 3.3517892360687256, "adapter_response": {"_message": "CREATE VIEW", "code": "CREATE VIEW", "rows_affected": -1}, "message": "CREATE VIEW", "failures": null, "unique_id": "model.jaffle_shop_metrics.stg_customers"}, {"status": "success", "timing": [{"name": "compile", "started_at": "2023-07-06T09:25:50.264008Z", "completed_at": "2023-07-06T09:25:51.210949Z"}, {"name": "execute", "started_at": "2023-07-06T09:25:51.228985Z", "completed_at": "2023-07-06T09:25:55.104549Z"}], "thread_id": "Thread-4 (worker)", "execution_time": 4.886475324630737, "adapter_response": {"_message": "SELECT 1", "code": "SELECT", "rows_affected": 1}, "message": "SELECT 1", "failures": null, "unique_id": "model.jaffle_shop_metrics.example_develop_metric"}, {"status": "success", "timing": [{"name": "compile", "started_at": "2023-07-06T09:25:50.544009Z", "completed_at": "2023-07-06T09:25:53.830216Z"}, {"name": "execute", "started_at": "2023-07-06T09:25:53.833216Z", "completed_at": "2023-07-06T09:25:55.109500Z"}], "thread_id": "Thread-1 (worker)", "execution_time": 4.880499601364136, "adapter_response": {"_message": "CREATE VIEW", "code": "CREATE VIEW", "rows_affected": -1}, "message": "CREATE VIEW", "failures": null, "unique_id": "model.jaffle_shop_metrics.stg_orders"}, {"status": "success", "timing": [{"name": "compile", "started_at": "2023-07-06T09:25:50.321969Z", "completed_at": "2023-07-06T09:25:50.734944Z"}, {"name": "execute", "started_at": "2023-07-06T09:25:51.191941Z", "completed_at": "2023-07-06T09:25:55.114507Z"}], "thread_id": "Thread-3 (worker)", "execution_time": 4.887414216995239, "adapter_response": {"_message": "SELECT 113", "code": "SELECT", "rows_affected": 113}, "message": "SELECT 113", "failures": null, "unique_id": "model.jaffle_shop_metrics.model_macro"}, {"status": "success", "timing": [{"name": "compile", "started_at": "2023-07-06T09:25:50.431959Z", "completed_at": "2023-07-06T09:25:51.208031Z"}, {"name": "execute", "started_at": "2023-07-06T09:25:51.213045Z", "completed_at": "2023-07-06T09:25:55.119490Z"}], "thread_id": "Thread-2 (worker)", "execution_time": 4.889554977416992, "adapter_response": {"_message": "SELECT 79", "code": "SELECT", "rows_affected": 79}, "message": "SELECT 79", "failures": null, "unique_id": "model.jaffle_shop_metrics.new_customers"}, {"status": "success", "timing": [{"name": "compile", "started_at": "2023-07-06T09:25:55.185522Z", "completed_at": "2023-07-06T09:25:55.214544Z"}, {"name": "execute", "started_at": "2023-07-06T09:25:55.219514Z", "completed_at": "2023-07-06T09:25:58.067548Z"}], "thread_id": "Thread-4 (worker)", "execution_time": 2.904017925262451, "adapter_response": {"_message": "SELECT 100", "code": "SELECT", "rows_affected": 100}, "message": "SELECT 100", "failures": null, "unique_id": "model.jaffle_shop_metrics.int_customer_order_history_joined"}, {"status": "success", "timing": [{"name": "compile", "started_at": "2023-07-06T09:25:55.196522Z", "completed_at": "2023-07-06T09:25:55.217521Z"}, {"name": "execute", "started_at": "2023-07-06T09:25:55.236633Z", "completed_at": "2023-07-06T09:25:58.072567Z"}], "thread_id": "Thread-1 (worker)", "execution_time": 2.906055212020874, "adapter_response": {"_message": "SELECT 2", "code": "SELECT", "rows_affected": 2}, "message": "SELECT 2", "failures": null, "unique_id": "model.jaffle_shop_metrics.int_order_payments_pivoted"}, {"status": "success", "timing": [{"name": "compile", "started_at": "2023-07-06T09:25:58.145614Z", "completed_at": "2023-07-06T09:25:58.171579Z"}, {"name": "execute", "started_at": "2023-07-06T09:25:58.193560Z", "completed_at": "2023-07-06T09:26:02.065568Z"}], "thread_id": "Thread-4 (worker)", "execution_time": 3.9601175785064697, "adapter_response": {"_message": "SELECT 2", "code": "SELECT", "rows_affected": 2}, "message": "SELECT 2", "failures": null, "unique_id": "model.jaffle_shop_metrics.orders_2 - Copy"}, {"status": "success", "timing": [{"name": "compile", "started_at": "2023-07-06T09:25:58.129570Z", "completed_at": "2023-07-06T09:25:58.168604Z"}, {"name": "execute", "started_at": "2023-07-06T09:25:58.176650Z", "completed_at": "2023-07-06T09:26:02.369593Z"}], "thread_id": "Thread-3 (worker)", "execution_time": 4.266819000244141, "adapter_response": {"_message": "SELECT 2", "code": "SELECT", "rows_affected": 2}, "message": "SELECT 2", "failures": null, "unique_id": "model.jaffle_shop_metrics.orders"}, {"status": "success", "timing": [{"name": "compile", "started_at": "2023-07-06T09:25:58.136560Z", "completed_at": "2023-07-06T09:25:58.173563Z"}, {"name": "execute", "started_at": "2023-07-06T09:25:58.205559Z", "completed_at": "2023-07-06T09:26:02.374473Z"}], "thread_id": "Thread-2 (worker)", "execution_time": 4.265881061553955, "adapter_response": {"_message": "SELECT 2", "code": "SELECT", "rows_affected": 2}, "message": "SELECT 2", "failures": null, "unique_id": "model.jaffle_shop_metrics.orders_2"}, {"status": "success", "timing": [{"name": "compile", "started_at": "2023-07-06T09:26:02.486462Z", "completed_at": "2023-07-06T09:26:02.545514Z"}, {"name": "execute", "started_at": "2023-07-06T09:26:02.563460Z", "completed_at": "2023-07-06T09:26:05.391759Z"}], "thread_id": "Thread-4 (worker)", "execution_time": 2.999246835708618, "adapter_response": {"_message": "SELECT 2", "code": "SELECT", "rows_affected": 2}, "message": "SELECT 2", "failures": null, "unique_id": "model.jaffle_shop_metrics.revenue"}, {"status": "success", "timing": [{"name": "compile", "started_at": "2023-07-06T09:26:02.412482Z", "completed_at": "2023-07-06T09:26:02.543473Z"}, {"name": "execute", "started_at": "2023-07-06T09:26:02.547481Z", "completed_at": "2023-07-06T09:26:05.395789Z"}], "thread_id": "Thread-1 (worker)", "execution_time": 3.0042805671691895, "adapter_response": {"_message": "SELECT 3", "code": "SELECT", "rows_affected": 3}, "message": "SELECT 3", "failures": null, "unique_id": "model.jaffle_shop_metrics.profit"}], "elapsed_time": 32.876009464263916, "args": {"select": [], "print": true, "quiet": false, "introspect": true, "partial_parse": true, "write_json": true, "use_colors": true, "strict_mode": false, "indirect_selection": "eager", "printer_width": 80, "which": "run", "send_anonymous_usage_stats": true, "log_path": "C:\\Users\\Talha\\OneDrive\\Desktop\\jaffle_shop_metrics\\logs", "project_dir": "C:\\Users\\Talha\\OneDrive\\Desktop\\jaffle_shop_metrics", "static_parser": true, "use_colors_file": true, "favor_state": false, "log_level_file": "debug", "log_format_file": "debug", "profiles_dir": "C:\\Users\\Talha\\OneDrive\\Desktop\\jaffle_shop_metrics", "exclude": [], "version_check": true, "log_format": "default", "cache_selected_only": false, "log_level": "info", "populate_cache": true, "vars": {}, "macro_debugging": false, "warn_error_options": {"include": [], "exclude": []}, "defer": false, "enable_legacy_logger": false}}